<?xml version="1.0" encoding="UTF-8"?>

<!-- generated on 2025-04-14 18:49:44.935657 by randomTrips.py UNKNOWN
<configuration>
    <net-file value="highway.net.xml"/>
    <output-trip-file value="bus.trips.xml"/>
    <route-file value="output.trips2.xml"/>
    <prefix value="bus"/>
    <trip-attributes value="departLane=&quot;best&quot; departSpeed=&quot;5&quot; "/>
    <lanes value="True"/>
    <fringe-factor value="100000"/>
    <seed value="30"/>
    <min-distance value="10.0"/>
    <max-distance value="500000.0"/>
    <validate value="True"/>
    <end value="854.0"/>
    <period value="1.4"/>
</configuration>
-->

<!-- generated on 2025-04-14 18:49:44 by Eclipse SUMO duarouter Version 1.19.0
<configuration xmlns:xsi="http://www.w3.org/2001/XMLSchema-instance" xsi:noNamespaceSchemaLocation="http://sumo.dlr.de/xsd/duarouterConfiguration.xsd">

    <input>
        <net-file value="highway.net.xml"/>
        <route-files value="bus.trips.xml"/>
    </input>

    <output>
        <output-file value="bus.trips.xml.tmp"/>
        <alternatives-output value="NUL"/>
        <write-trips value="true"/>
    </output>

    <time>
        <begin value="0"/>
        <end value="854.0"/>
    </time>

    <report>
        <no-warnings value="true"/>
        <ignore-errors value="true"/>
        <no-step-log value="true"/>
    </report>

</configuration>
-->

<routes xmlns:xsi="http://www.w3.org/2001/XMLSchema-instance" xsi:noNamespaceSchemaLocation="http://sumo.dlr.de/xsd/routes_file.xsd">
    <trip id="bus0" type="bus0" depart="0.00" departLane="best" departSpeed="5.00" from="E0" to="E1"/>
    <trip id="bus1" type="bus1" depart="1.40" departLane="best" departSpeed="5.00" from="E0" to="E1"/>
    <trip id="bus2" type="bus2" depart="2.80" departLane="best" departSpeed="5.00" from="E0" to="E1"/>
    <trip id="bus3" type="bus3" depart="4.20" departLane="best" departSpeed="5.00" from="E0" to="E1"/>
    <trip id="bus4" type="bus4" depart="5.60" departLane="best" departSpeed="5.00" from="E0" to="E1"/>
    <trip id="bus5" type="bus5" depart="7.00" departLane="best" departSpeed="5.00" from="E0" to="E1"/>
    <trip id="bus6" type="bus6" depart="8.40" departLane="best" departSpeed="5.00" from="E0" to="E1"/>
    <trip id="bus7" type="bus7" depart="9.80" departLane="best" departSpeed="5.00" from="E0" to="E1"/>
    <trip id="bus8" type="bus8" depart="11.20" departLane="best" departSpeed="5.00" from="E0" to="E1"/>
    <trip id="bus9" type="bus9" depart="12.60" departLane="best" departSpeed="5.00" from="E0" to="E1"/>
    <trip id="bus10" type="bus10" depart="14.00" departLane="best" departSpeed="5.00" from="E0" to="E1"/>
    <trip id="bus11" type="bus11" depart="15.40" departLane="best" departSpeed="5.00" from="E0" to="E1"/>
    <trip id="bus12" type="bus12" depart="16.80" departLane="best" departSpeed="5.00" from="E0" to="E1"/>
    <trip id="bus13" type="bus13" depart="18.20" departLane="best" departSpeed="5.00" from="E0" to="E1"/>
    <trip id="bus14" type="bus14" depart="19.60" departLane="best" departSpeed="5.00" from="E0" to="E1"/>
    <trip id="bus15" type="bus15" depart="21.00" departLane="best" departSpeed="5.00" from="E0" to="E1"/>
    <trip id="bus16" type="bus16" depart="22.40" departLane="best" departSpeed="5.00" from="E0" to="E1"/>
    <trip id="bus17" type="bus17" depart="23.80" departLane="best" departSpeed="5.00" from="E0" to="E1"/>
    <trip id="bus18" type="bus18" depart="25.20" departLane="best" departSpeed="5.00" from="E0" to="E1"/>
    <trip id="bus19" type="bus19" depart="26.60" departLane="best" departSpeed="5.00" from="E0" to="E1"/>
    <trip id="bus20" type="bus20" depart="28.00" departLane="best" departSpeed="5.00" from="E0" to="E1"/>
    <trip id="bus21" type="bus21" depart="29.40" departLane="best" departSpeed="5.00" from="E0" to="E1"/>
    <trip id="bus22" type="bus22" depart="30.80" departLane="best" departSpeed="5.00" from="E0" to="E1"/>
    <trip id="bus23" type="bus23" depart="32.20" departLane="best" departSpeed="5.00" from="E0" to="E1"/>
    <trip id="bus24" type="bus24" depart="33.60" departLane="best" departSpeed="5.00" from="E0" to="E1"/>
    <trip id="bus25" type="bus25" depart="35.00" departLane="best" departSpeed="5.00" from="E0" to="E1"/>
    <trip id="bus26" type="bus26" depart="36.40" departLane="best" departSpeed="5.00" from="E0" to="E1"/>
    <trip id="bus27" type="bus27" depart="37.80" departLane="best" departSpeed="5.00" from="E0" to="E1"/>
    <trip id="bus28" type="bus28" depart="39.20" departLane="best" departSpeed="5.00" from="E0" to="E1"/>
    <trip id="bus29" type="bus29" depart="40.60" departLane="best" departSpeed="5.00" from="E0" to="E1"/>
    <trip id="bus30" type="bus30" depart="42.00" departLane="best" departSpeed="5.00" from="E0" to="E1"/>
    <trip id="bus31" type="bus31" depart="43.40" departLane="best" departSpeed="5.00" from="E0" to="E1"/>
    <trip id="bus32" type="bus32" depart="44.80" departLane="best" departSpeed="5.00" from="E0" to="E1"/>
    <trip id="bus33" type="bus33" depart="46.20" departLane="best" departSpeed="5.00" from="E0" to="E1"/>
    <trip id="bus34" type="bus34" depart="47.60" departLane="best" departSpeed="5.00" from="E0" to="E1"/>
    <trip id="bus35" type="bus35" depart="49.00" departLane="best" departSpeed="5.00" from="E0" to="E1"/>
    <trip id="bus36" type="bus36" depart="50.40" departLane="best" departSpeed="5.00" from="E0" to="E1"/>
    <trip id="bus37" type="bus37" depart="51.80" departLane="best" departSpeed="5.00" from="E0" to="E1"/>
    <trip id="bus38" type="bus38" depart="53.20" departLane="best" departSpeed="5.00" from="E0" to="E1"/>
    <trip id="bus39" type="bus39" depart="54.60" departLane="best" departSpeed="5.00" from="E0" to="E1"/>
    <trip id="bus40" type="bus40" depart="56.00" departLane="best" departSpeed="5.00" from="E0" to="E1"/>
    <trip id="bus41" type="bus41" depart="57.40" departLane="best" departSpeed="5.00" from="E0" to="E1"/>
    <trip id="bus42" type="bus42" depart="58.80" departLane="best" departSpeed="5.00" from="E0" to="E1"/>
    <trip id="bus43" type="bus43" depart="60.20" departLane="best" departSpeed="5.00" from="E0" to="E1"/>
    <trip id="bus44" type="bus44" depart="61.60" departLane="best" departSpeed="5.00" from="E0" to="E1"/>
    <trip id="bus45" type="bus45" depart="63.00" departLane="best" departSpeed="5.00" from="E0" to="E1"/>
    <trip id="bus46" type="bus46" depart="64.40" departLane="best" departSpeed="5.00" from="E0" to="E1"/>
    <trip id="bus47" type="bus47" depart="65.80" departLane="best" departSpeed="5.00" from="E0" to="E1"/>
    <trip id="bus48" type="bus48" depart="67.20" departLane="best" departSpeed="5.00" from="E0" to="E1"/>
    <trip id="bus49" type="bus49" depart="68.60" departLane="best" departSpeed="5.00" from="E0" to="E1"/>
    <trip id="bus50" type="bus50" depart="70.00" departLane="best" departSpeed="5.00" from="E0" to="E1"/>
    <trip id="bus51" type="bus51" depart="71.40" departLane="best" departSpeed="5.00" from="E0" to="E1"/>
    <trip id="bus52" type="bus52" depart="72.80" departLane="best" departSpeed="5.00" from="E0" to="E1"/>
    <trip id="bus53" type="bus53" depart="74.20" departLane="best" departSpeed="5.00" from="E0" to="E1"/>
    <trip id="bus54" type="bus54" depart="75.60" departLane="best" departSpeed="5.00" from="E0" to="E1"/>
    <trip id="bus55" type="bus55" depart="77.00" departLane="best" departSpeed="5.00" from="E0" to="E1"/>
    <trip id="bus56" type="bus56" depart="78.40" departLane="best" departSpeed="5.00" from="E0" to="E1"/>
    <trip id="bus57" type="bus57" depart="79.80" departLane="best" departSpeed="5.00" from="E0" to="E1"/>
    <trip id="bus58" type="bus58" depart="81.20" departLane="best" departSpeed="5.00" from="E0" to="E1"/>
    <trip id="bus59" type="bus59" depart="82.60" departLane="best" departSpeed="5.00" from="E0" to="E1"/>
    <trip id="bus60" type="bus60" depart="84.00" departLane="best" departSpeed="5.00" from="E0" to="E1"/>
    <trip id="bus61" type="bus61" depart="85.40" departLane="best" departSpeed="5.00" from="E0" to="E1"/>
    <trip id="bus62" type="bus62" depart="86.80" departLane="best" departSpeed="5.00" from="E0" to="E1"/>
    <trip id="bus63" type="bus63" depart="88.20" departLane="best" departSpeed="5.00" from="E0" to="E1"/>
    <trip id="bus64" type="bus64" depart="89.60" departLane="best" departSpeed="5.00" from="E0" to="E1"/>
    <trip id="bus65" type="bus65" depart="91.00" departLane="best" departSpeed="5.00" from="E0" to="E1"/>
    <trip id="bus66" type="bus66" depart="92.40" departLane="best" departSpeed="5.00" from="E0" to="E1"/>
    <trip id="bus67" type="bus67" depart="93.80" departLane="best" departSpeed="5.00" from="E0" to="E1"/>
    <trip id="bus68" type="bus68" depart="95.20" departLane="best" departSpeed="5.00" from="E0" to="E1"/>
    <trip id="bus69" type="bus69" depart="96.60" departLane="best" departSpeed="5.00" from="E0" to="E1"/>
    <trip id="bus70" type="bus70" depart="98.00" departLane="best" departSpeed="5.00" from="E0" to="E1"/>
    <trip id="bus71" type="bus71" depart="99.40" departLane="best" departSpeed="5.00" from="E0" to="E1"/>
    <trip id="bus72" type="bus72" depart="100.80" departLane="best" departSpeed="5.00" from="E0" to="E1"/>
    <trip id="bus73" type="bus73" depart="102.20" departLane="best" departSpeed="5.00" from="E0" to="E1"/>
    <trip id="bus74" type="bus74" depart="103.60" departLane="best" departSpeed="5.00" from="E0" to="E1"/>
    <trip id="bus75" type="bus75" depart="105.00" departLane="best" departSpeed="5.00" from="E0" to="E1"/>
    <trip id="bus76" type="bus76" depart="106.40" departLane="best" departSpeed="5.00" from="E0" to="E1"/>
    <trip id="bus77" type="bus77" depart="107.80" departLane="best" departSpeed="5.00" from="E0" to="E1"/>
    <trip id="bus78" type="bus78" depart="109.20" departLane="best" departSpeed="5.00" from="E0" to="E1"/>
    <trip id="bus79" type="bus79" depart="110.60" departLane="best" departSpeed="5.00" from="E0" to="E1"/>
    <trip id="bus80" type="bus80" depart="112.00" departLane="best" departSpeed="5.00" from="E0" to="E1"/>
    <trip id="bus81" type="bus81" depart="113.40" departLane="best" departSpeed="5.00" from="E0" to="E1"/>
    <trip id="bus82" type="bus82" depart="114.80" departLane="best" departSpeed="5.00" from="E0" to="E1"/>
    <trip id="bus83" type="bus83" depart="116.20" departLane="best" departSpeed="5.00" from="E0" to="E1"/>
    <trip id="bus84" type="bus84" depart="117.60" departLane="best" departSpeed="5.00" from="E0" to="E1"/>
    <trip id="bus85" type="bus85" depart="119.00" departLane="best" departSpeed="5.00" from="E0" to="E1"/>
    <trip id="bus86" type="bus86" depart="120.40" departLane="best" departSpeed="5.00" from="E0" to="E1"/>
    <trip id="bus87" type="bus87" depart="121.80" departLane="best" departSpeed="5.00" from="E0" to="E1"/>
    <trip id="bus88" type="bus88" depart="123.20" departLane="best" departSpeed="5.00" from="E0" to="E1"/>
    <trip id="bus89" type="bus89" depart="124.60" departLane="best" departSpeed="5.00" from="E0" to="E1"/>
    <trip id="bus90" type="bus90" depart="126.00" departLane="best" departSpeed="5.00" from="E0" to="E1"/>
    <trip id="bus91" type="bus91" depart="127.40" departLane="best" departSpeed="5.00" from="E0" to="E1"/>
    <trip id="bus92" type="bus92" depart="128.80" departLane="best" departSpeed="5.00" from="E0" to="E1"/>
    <trip id="bus93" type="bus93" depart="130.20" departLane="best" departSpeed="5.00" from="E0" to="E1"/>
    <trip id="bus94" type="bus94" depart="131.60" departLane="best" departSpeed="5.00" from="E0" to="E1"/>
    <trip id="bus95" type="bus95" depart="133.00" departLane="best" departSpeed="5.00" from="E0" to="E1"/>
    <trip id="bus96" type="bus96" depart="134.40" departLane="best" departSpeed="5.00" from="E0" to="E1"/>
    <trip id="bus97" type="bus97" depart="135.80" departLane="best" departSpeed="5.00" from="E0" to="E1"/>
    <trip id="bus98" type="bus98" depart="137.20" departLane="best" departSpeed="5.00" from="E0" to="E1"/>
    <trip id="bus99" type="bus99" depart="138.60" departLane="best" departSpeed="5.00" from="E0" to="E1"/>
    <trip id="bus100" type="bus100" depart="140.00" departLane="best" departSpeed="5.00" from="E0" to="E1"/>
    <trip id="bus101" type="bus101" depart="141.40" departLane="best" departSpeed="5.00" from="E0" to="E1"/>
    <trip id="bus102" type="bus102" depart="142.80" departLane="best" departSpeed="5.00" from="E0" to="E1"/>
    <trip id="bus103" type="bus103" depart="144.20" departLane="best" departSpeed="5.00" from="E0" to="E1"/>
    <trip id="bus104" type="bus104" depart="145.60" departLane="best" departSpeed="5.00" from="E0" to="E1"/>
    <trip id="bus105" type="bus105" depart="147.00" departLane="best" departSpeed="5.00" from="E0" to="E1"/>
    <trip id="bus106" type="bus106" depart="148.40" departLane="best" departSpeed="5.00" from="E0" to="E1"/>
    <trip id="bus107" type="bus107" depart="149.80" departLane="best" departSpeed="5.00" from="E0" to="E1"/>
    <trip id="bus108" type="bus108" depart="151.20" departLane="best" departSpeed="5.00" from="E0" to="E1"/>
    <trip id="bus109" type="bus109" depart="152.60" departLane="best" departSpeed="5.00" from="E0" to="E1"/>
    <trip id="bus110" type="bus110" depart="154.00" departLane="best" departSpeed="5.00" from="E0" to="E1"/>
    <trip id="bus111" type="bus111" depart="155.40" departLane="best" departSpeed="5.00" from="E0" to="E1"/>
    <trip id="bus112" type="bus112" depart="156.80" departLane="best" departSpeed="5.00" from="E0" to="E1"/>
    <trip id="bus113" type="bus113" depart="158.20" departLane="best" departSpeed="5.00" from="E0" to="E1"/>
    <trip id="bus114" type="bus114" depart="159.60" departLane="best" departSpeed="5.00" from="E0" to="E1"/>
    <trip id="bus115" type="bus115" depart="161.00" departLane="best" departSpeed="5.00" from="E0" to="E1"/>
    <trip id="bus116" type="bus116" depart="162.40" departLane="best" departSpeed="5.00" from="E0" to="E1"/>
    <trip id="bus117" type="bus117" depart="163.80" departLane="best" departSpeed="5.00" from="E0" to="E1"/>
    <trip id="bus118" type="bus118" depart="165.20" departLane="best" departSpeed="5.00" from="E0" to="E1"/>
    <trip id="bus119" type="bus119" depart="166.60" departLane="best" departSpeed="5.00" from="E0" to="E1"/>
    <trip id="bus120" type="bus120" depart="168.00" departLane="best" departSpeed="5.00" from="E0" to="E1"/>
    <trip id="bus121" type="bus121" depart="169.40" departLane="best" departSpeed="5.00" from="E0" to="E1"/>
    <trip id="bus122" type="bus122" depart="170.80" departLane="best" departSpeed="5.00" from="E0" to="E1"/>
    <trip id="bus123" type="bus123" depart="172.20" departLane="best" departSpeed="5.00" from="E0" to="E1"/>
    <trip id="bus124" type="bus124" depart="173.60" departLane="best" departSpeed="5.00" from="E0" to="E1"/>
    <trip id="bus125" type="bus125" depart="175.00" departLane="best" departSpeed="5.00" from="E0" to="E1"/>
    <trip id="bus126" type="bus126" depart="176.40" departLane="best" departSpeed="5.00" from="E0" to="E1"/>
    <trip id="bus127" type="bus127" depart="177.80" departLane="best" departSpeed="5.00" from="E0" to="E1"/>
    <trip id="bus128" type="bus128" depart="179.20" departLane="best" departSpeed="5.00" from="E0" to="E1"/>
    <trip id="bus129" type="bus129" depart="180.60" departLane="best" departSpeed="5.00" from="E0" to="E1"/>
    <trip id="bus130" type="bus130" depart="182.00" departLane="best" departSpeed="5.00" from="E0" to="E1"/>
    <trip id="bus131" type="bus131" depart="183.40" departLane="best" departSpeed="5.00" from="E0" to="E1"/>
    <trip id="bus132" type="bus132" depart="184.80" departLane="best" departSpeed="5.00" from="E0" to="E1"/>
    <trip id="bus133" type="bus133" depart="186.20" departLane="best" departSpeed="5.00" from="E0" to="E1"/>
    <trip id="bus134" type="bus134" depart="187.60" departLane="best" departSpeed="5.00" from="E0" to="E1"/>
    <trip id="bus135" type="bus135" depart="189.00" departLane="best" departSpeed="5.00" from="E0" to="E1"/>
    <trip id="bus136" type="bus136" depart="190.40" departLane="best" departSpeed="5.00" from="E0" to="E1"/>
    <trip id="bus137" type="bus137" depart="191.80" departLane="best" departSpeed="5.00" from="E0" to="E1"/>
    <trip id="bus138" type="bus138" depart="193.20" departLane="best" departSpeed="5.00" from="E0" to="E1"/>
    <trip id="bus139" type="bus139" depart="194.60" departLane="best" departSpeed="5.00" from="E0" to="E1"/>
    <trip id="bus140" type="bus140" depart="196.00" departLane="best" departSpeed="5.00" from="E0" to="E1"/>
    <trip id="bus141" type="bus141" depart="197.40" departLane="best" departSpeed="5.00" from="E0" to="E1"/>
    <trip id="bus142" type="bus142" depart="198.80" departLane="best" departSpeed="5.00" from="E0" to="E1"/>
    <trip id="bus143" type="bus143" depart="200.20" departLane="best" departSpeed="5.00" from="E0" to="E1"/>
    <trip id="bus144" type="bus144" depart="201.60" departLane="best" departSpeed="5.00" from="E0" to="E1"/>
    <trip id="bus145" type="bus145" depart="203.00" departLane="best" departSpeed="5.00" from="E0" to="E1"/>
    <trip id="bus146" type="bus146" depart="204.40" departLane="best" departSpeed="5.00" from="E0" to="E1"/>
    <trip id="bus147" type="bus147" depart="205.80" departLane="best" departSpeed="5.00" from="E0" to="E1"/>
    <trip id="bus148" type="bus148" depart="207.20" departLane="best" departSpeed="5.00" from="E0" to="E1"/>
    <trip id="bus149" type="bus149" depart="208.60" departLane="best" departSpeed="5.00" from="E0" to="E1"/>
    <trip id="bus150" type="bus150" depart="210.00" departLane="best" departSpeed="5.00" from="E0" to="E1"/>
    <trip id="bus151" type="bus151" depart="211.40" departLane="best" departSpeed="5.00" from="E0" to="E1"/>
    <trip id="bus152" type="bus152" depart="212.80" departLane="best" departSpeed="5.00" from="E0" to="E1"/>
    <trip id="bus153" type="bus153" depart="214.20" departLane="best" departSpeed="5.00" from="E0" to="E1"/>
    <trip id="bus154" type="bus154" depart="215.60" departLane="best" departSpeed="5.00" from="E0" to="E1"/>
    <trip id="bus155" type="bus155" depart="217.00" departLane="best" departSpeed="5.00" from="E0" to="E1"/>
    <trip id="bus156" type="bus156" depart="218.40" departLane="best" departSpeed="5.00" from="E0" to="E1"/>
    <trip id="bus157" type="bus157" depart="219.80" departLane="best" departSpeed="5.00" from="E0" to="E1"/>
    <trip id="bus158" type="bus158" depart="221.20" departLane="best" departSpeed="5.00" from="E0" to="E1"/>
    <trip id="bus159" type="bus159" depart="222.60" departLane="best" departSpeed="5.00" from="E0" to="E1"/>
    <trip id="bus160" type="bus160" depart="224.00" departLane="best" departSpeed="5.00" from="E0" to="E1"/>
    <trip id="bus161" type="bus161" depart="225.40" departLane="best" departSpeed="5.00" from="E0" to="E1"/>
    <trip id="bus162" type="bus162" depart="226.80" departLane="best" departSpeed="5.00" from="E0" to="E1"/>
    <trip id="bus163" type="bus163" depart="228.20" departLane="best" departSpeed="5.00" from="E0" to="E1"/>
    <trip id="bus164" type="bus164" depart="229.60" departLane="best" departSpeed="5.00" from="E0" to="E1"/>
    <trip id="bus165" type="bus165" depart="231.00" departLane="best" departSpeed="5.00" from="E0" to="E1"/>
    <trip id="bus166" type="bus166" depart="232.40" departLane="best" departSpeed="5.00" from="E0" to="E1"/>
    <trip id="bus167" type="bus167" depart="233.80" departLane="best" departSpeed="5.00" from="E0" to="E1"/>
    <trip id="bus168" type="bus168" depart="235.20" departLane="best" departSpeed="5.00" from="E0" to="E1"/>
    <trip id="bus169" type="bus169" depart="236.60" departLane="best" departSpeed="5.00" from="E0" to="E1"/>
    <trip id="bus170" type="bus170" depart="238.00" departLane="best" departSpeed="5.00" from="E0" to="E1"/>
    <trip id="bus171" type="bus171" depart="239.40" departLane="best" departSpeed="5.00" from="E0" to="E1"/>
    <trip id="bus172" type="bus172" depart="240.80" departLane="best" departSpeed="5.00" from="E0" to="E1"/>
    <trip id="bus173" type="bus173" depart="242.20" departLane="best" departSpeed="5.00" from="E0" to="E1"/>
    <trip id="bus174" type="bus174" depart="243.60" departLane="best" departSpeed="5.00" from="E0" to="E1"/>
    <trip id="bus175" type="bus175" depart="245.00" departLane="best" departSpeed="5.00" from="E0" to="E1"/>
    <trip id="bus176" type="bus176" depart="246.40" departLane="best" departSpeed="5.00" from="E0" to="E1"/>
    <trip id="bus177" type="bus177" depart="247.80" departLane="best" departSpeed="5.00" from="E0" to="E1"/>
    <trip id="bus178" type="bus178" depart="249.20" departLane="best" departSpeed="5.00" from="E0" to="E1"/>
    <trip id="bus179" type="bus179" depart="250.60" departLane="best" departSpeed="5.00" from="E0" to="E1"/>
    <trip id="bus180" type="bus180" depart="252.00" departLane="best" departSpeed="5.00" from="E0" to="E1"/>
    <trip id="bus181" type="bus181" depart="253.40" departLane="best" departSpeed="5.00" from="E0" to="E1"/>
    <trip id="bus182" type="bus182" depart="254.80" departLane="best" departSpeed="5.00" from="E0" to="E1"/>
    <trip id="bus183" type="bus183" depart="256.20" departLane="best" departSpeed="5.00" from="E0" to="E1"/>
    <trip id="bus184" type="bus184" depart="257.60" departLane="best" departSpeed="5.00" from="E0" to="E1"/>
    <trip id="bus185" type="bus185" depart="259.00" departLane="best" departSpeed="5.00" from="E0" to="E1"/>
    <trip id="bus186" type="bus186" depart="260.40" departLane="best" departSpeed="5.00" from="E0" to="E1"/>
    <trip id="bus187" type="bus187" depart="261.80" departLane="best" departSpeed="5.00" from="E0" to="E1"/>
    <trip id="bus188" type="bus188" depart="263.20" departLane="best" departSpeed="5.00" from="E0" to="E1"/>
    <trip id="bus189" type="bus189" depart="264.60" departLane="best" departSpeed="5.00" from="E0" to="E1"/>
    <trip id="bus190" type="bus190" depart="266.00" departLane="best" departSpeed="5.00" from="E0" to="E1"/>
    <trip id="bus191" type="bus191" depart="267.40" departLane="best" departSpeed="5.00" from="E0" to="E1"/>
    <trip id="bus192" type="bus192" depart="268.80" departLane="best" departSpeed="5.00" from="E0" to="E1"/>
    <trip id="bus193" type="bus193" depart="270.20" departLane="best" departSpeed="5.00" from="E0" to="E1"/>
    <trip id="bus194" type="bus194" depart="271.60" departLane="best" departSpeed="5.00" from="E0" to="E1"/>
    <trip id="bus195" type="bus195" depart="273.00" departLane="best" departSpeed="5.00" from="E0" to="E1"/>
    <trip id="bus196" type="bus196" depart="274.40" departLane="best" departSpeed="5.00" from="E0" to="E1"/>
    <trip id="bus197" type="bus197" depart="275.80" departLane="best" departSpeed="5.00" from="E0" to="E1"/>
    <trip id="bus198" type="bus198" depart="277.20" departLane="best" departSpeed="5.00" from="E0" to="E1"/>
    <trip id="bus199" type="bus199" depart="278.60" departLane="best" departSpeed="5.00" from="E0" to="E1"/>
    <trip id="bus200" type="bus200" depart="280.00" departLane="best" departSpeed="5.00" from="E0" to="E1"/>
    <trip id="bus201" type="bus201" depart="281.40" departLane="best" departSpeed="5.00" from="E0" to="E1"/>
    <trip id="bus202" type="bus202" depart="282.80" departLane="best" departSpeed="5.00" from="E0" to="E1"/>
    <trip id="bus203" type="bus203" depart="284.20" departLane="best" departSpeed="5.00" from="E0" to="E1"/>
    <trip id="bus204" type="bus204" depart="285.60" departLane="best" departSpeed="5.00" from="E0" to="E1"/>
    <trip id="bus205" type="bus205" depart="287.00" departLane="best" departSpeed="5.00" from="E0" to="E1"/>
    <trip id="bus206" type="bus206" depart="288.40" departLane="best" departSpeed="5.00" from="E0" to="E1"/>
    <trip id="bus207" type="bus207" depart="289.80" departLane="best" departSpeed="5.00" from="E0" to="E1"/>
    <trip id="bus208" type="bus208" depart="291.20" departLane="best" departSpeed="5.00" from="E0" to="E1"/>
    <trip id="bus209" type="bus209" depart="292.60" departLane="best" departSpeed="5.00" from="E0" to="E1"/>
    <trip id="bus210" type="bus210" depart="294.00" departLane="best" departSpeed="5.00" from="E0" to="E1"/>
    <trip id="bus211" type="bus211" depart="295.40" departLane="best" departSpeed="5.00" from="E0" to="E1"/>
    <trip id="bus212" type="bus212" depart="296.80" departLane="best" departSpeed="5.00" from="E0" to="E1"/>
    <trip id="bus213" type="bus213" depart="298.20" departLane="best" departSpeed="5.00" from="E0" to="E1"/>
    <trip id="bus214" type="bus214" depart="299.60" departLane="best" departSpeed="5.00" from="E0" to="E1"/>
    <trip id="bus215" type="bus215" depart="301.00" departLane="best" departSpeed="5.00" from="E0" to="E1"/>
    <trip id="bus216" type="bus216" depart="302.40" departLane="best" departSpeed="5.00" from="E0" to="E1"/>
    <trip id="bus217" type="bus217" depart="303.80" departLane="best" departSpeed="5.00" from="E0" to="E1"/>
    <trip id="bus218" type="bus218" depart="305.20" departLane="best" departSpeed="5.00" from="E0" to="E1"/>
    <trip id="bus219" type="bus219" depart="306.60" departLane="best" departSpeed="5.00" from="E0" to="E1"/>
    <trip id="bus220" type="bus220" depart="308.00" departLane="best" departSpeed="5.00" from="E0" to="E1"/>
    <trip id="bus221" type="bus221" depart="309.40" departLane="best" departSpeed="5.00" from="E0" to="E1"/>
    <trip id="bus222" type="bus222" depart="310.80" departLane="best" departSpeed="5.00" from="E0" to="E1"/>
    <trip id="bus223" type="bus223" depart="312.20" departLane="best" departSpeed="5.00" from="E0" to="E1"/>
    <trip id="bus224" type="bus224" depart="313.60" departLane="best" departSpeed="5.00" from="E0" to="E1"/>
    <trip id="bus225" type="bus225" depart="315.00" departLane="best" departSpeed="5.00" from="E0" to="E1"/>
    <trip id="bus226" type="bus226" depart="316.40" departLane="best" departSpeed="5.00" from="E0" to="E1"/>
    <trip id="bus227" type="bus227" depart="317.80" departLane="best" departSpeed="5.00" from="E0" to="E1"/>
    <trip id="bus228" type="bus228" depart="319.20" departLane="best" departSpeed="5.00" from="E0" to="E1"/>
    <trip id="bus229" type="bus229" depart="320.60" departLane="best" departSpeed="5.00" from="E0" to="E1"/>
    <trip id="bus230" type="bus230" depart="322.00" departLane="best" departSpeed="5.00" from="E0" to="E1"/>
    <trip id="bus231" type="bus231" depart="323.40" departLane="best" departSpeed="5.00" from="E0" to="E1"/>
    <trip id="bus232" type="bus232" depart="324.80" departLane="best" departSpeed="5.00" from="E0" to="E1"/>
    <trip id="bus233" type="bus233" depart="326.20" departLane="best" departSpeed="5.00" from="E0" to="E1"/>
    <trip id="bus234" type="bus234" depart="327.60" departLane="best" departSpeed="5.00" from="E0" to="E1"/>
    <trip id="bus235" type="bus235" depart="329.00" departLane="best" departSpeed="5.00" from="E0" to="E1"/>
    <trip id="bus236" type="bus236" depart="330.40" departLane="best" departSpeed="5.00" from="E0" to="E1"/>
    <trip id="bus237" type="bus237" depart="331.80" departLane="best" departSpeed="5.00" from="E0" to="E1"/>
    <trip id="bus238" type="bus238" depart="333.20" departLane="best" departSpeed="5.00" from="E0" to="E1"/>
    <trip id="bus239" type="bus239" depart="334.60" departLane="best" departSpeed="5.00" from="E0" to="E1"/>
    <trip id="bus240" type="bus240" depart="336.00" departLane="best" departSpeed="5.00" from="E0" to="E1"/>
    <trip id="bus241" type="bus241" depart="337.40" departLane="best" departSpeed="5.00" from="E0" to="E1"/>
    <trip id="bus242" type="bus242" depart="338.80" departLane="best" departSpeed="5.00" from="E0" to="E1"/>
    <trip id="bus243" type="bus243" depart="340.20" departLane="best" departSpeed="5.00" from="E0" to="E1"/>
    <trip id="bus244" type="bus244" depart="341.60" departLane="best" departSpeed="5.00" from="E0" to="E1"/>
    <trip id="bus245" type="bus245" depart="343.00" departLane="best" departSpeed="5.00" from="E0" to="E1"/>
    <trip id="bus246" type="bus246" depart="344.40" departLane="best" departSpeed="5.00" from="E0" to="E1"/>
    <trip id="bus247" type="bus247" depart="345.80" departLane="best" departSpeed="5.00" from="E0" to="E1"/>
    <trip id="bus248" type="bus248" depart="347.20" departLane="best" departSpeed="5.00" from="E0" to="E1"/>
    <trip id="bus249" type="bus249" depart="348.60" departLane="best" departSpeed="5.00" from="E0" to="E1"/>
    <trip id="bus250" type="bus250" depart="350.00" departLane="best" departSpeed="5.00" from="E0" to="E1"/>
    <trip id="bus251" type="bus251" depart="351.40" departLane="best" departSpeed="5.00" from="E0" to="E1"/>
    <trip id="bus252" type="bus252" depart="352.80" departLane="best" departSpeed="5.00" from="E0" to="E1"/>
    <trip id="bus253" type="bus253" depart="354.20" departLane="best" departSpeed="5.00" from="E0" to="E1"/>
    <trip id="bus254" type="bus254" depart="355.60" departLane="best" departSpeed="5.00" from="E0" to="E1"/>
    <trip id="bus255" type="bus255" depart="357.00" departLane="best" departSpeed="5.00" from="E0" to="E1"/>
    <trip id="bus256" type="bus256" depart="358.40" departLane="best" departSpeed="5.00" from="E0" to="E1"/>
    <trip id="bus257" type="bus257" depart="359.80" departLane="best" departSpeed="5.00" from="E0" to="E1"/>
    <trip id="bus258" type="bus258" depart="361.20" departLane="best" departSpeed="5.00" from="E0" to="E1"/>
    <trip id="bus259" type="bus259" depart="362.60" departLane="best" departSpeed="5.00" from="E0" to="E1"/>
    <trip id="bus260" type="bus260" depart="364.00" departLane="best" departSpeed="5.00" from="E0" to="E1"/>
    <trip id="bus261" type="bus261" depart="365.40" departLane="best" departSpeed="5.00" from="E0" to="E1"/>
    <trip id="bus262" type="bus262" depart="366.80" departLane="best" departSpeed="5.00" from="E0" to="E1"/>
    <trip id="bus263" type="bus263" depart="368.20" departLane="best" departSpeed="5.00" from="E0" to="E1"/>
    <trip id="bus264" type="bus264" depart="369.60" departLane="best" departSpeed="5.00" from="E0" to="E1"/>
    <trip id="bus265" type="bus265" depart="371.00" departLane="best" departSpeed="5.00" from="E0" to="E1"/>
    <trip id="bus266" type="bus266" depart="372.40" departLane="best" departSpeed="5.00" from="E0" to="E1"/>
    <trip id="bus267" type="bus267" depart="373.80" departLane="best" departSpeed="5.00" from="E0" to="E1"/>
    <trip id="bus268" type="bus268" depart="375.20" departLane="best" departSpeed="5.00" from="E0" to="E1"/>
    <trip id="bus269" type="bus269" depart="376.60" departLane="best" departSpeed="5.00" from="E0" to="E1"/>
    <trip id="bus270" type="bus270" depart="378.00" departLane="best" departSpeed="5.00" from="E0" to="E1"/>
    <trip id="bus271" type="bus271" depart="379.40" departLane="best" departSpeed="5.00" from="E0" to="E1"/>
    <trip id="bus272" type="bus272" depart="380.80" departLane="best" departSpeed="5.00" from="E0" to="E1"/>
    <trip id="bus273" type="bus273" depart="382.20" departLane="best" departSpeed="5.00" from="E0" to="E1"/>
    <trip id="bus274" type="bus274" depart="383.60" departLane="best" departSpeed="5.00" from="E0" to="E1"/>
    <trip id="bus275" type="bus275" depart="385.00" departLane="best" departSpeed="5.00" from="E0" to="E1"/>
    <trip id="bus276" type="bus276" depart="386.40" departLane="best" departSpeed="5.00" from="E0" to="E1"/>
    <trip id="bus277" type="bus277" depart="387.80" departLane="best" departSpeed="5.00" from="E0" to="E1"/>
    <trip id="bus278" type="bus278" depart="389.20" departLane="best" departSpeed="5.00" from="E0" to="E1"/>
    <trip id="bus279" type="bus279" depart="390.60" departLane="best" departSpeed="5.00" from="E0" to="E1"/>
    <trip id="bus280" type="bus280" depart="392.00" departLane="best" departSpeed="5.00" from="E0" to="E1"/>
    <trip id="bus281" type="bus281" depart="393.40" departLane="best" departSpeed="5.00" from="E0" to="E1"/>
    <trip id="bus282" type="bus282" depart="394.80" departLane="best" departSpeed="5.00" from="E0" to="E1"/>
    <trip id="bus283" type="bus283" depart="396.20" departLane="best" departSpeed="5.00" from="E0" to="E1"/>
    <trip id="bus284" type="bus284" depart="397.60" departLane="best" departSpeed="5.00" from="E0" to="E1"/>
    <trip id="bus285" type="bus285" depart="399.00" departLane="best" departSpeed="5.00" from="E0" to="E1"/>
    <trip id="bus286" type="bus286" depart="400.40" departLane="best" departSpeed="5.00" from="E0" to="E1"/>
    <trip id="bus287" type="bus287" depart="401.80" departLane="best" departSpeed="5.00" from="E0" to="E1"/>
    <trip id="bus288" type="bus288" depart="403.20" departLane="best" departSpeed="5.00" from="E0" to="E1"/>
    <trip id="bus289" type="bus289" depart="404.60" departLane="best" departSpeed="5.00" from="E0" to="E1"/>
    <trip id="bus290" type="bus290" depart="406.00" departLane="best" departSpeed="5.00" from="E0" to="E1"/>
    <trip id="bus291" type="bus291" depart="407.40" departLane="best" departSpeed="5.00" from="E0" to="E1"/>
    <trip id="bus292" type="bus292" depart="408.80" departLane="best" departSpeed="5.00" from="E0" to="E1"/>
    <trip id="bus293" type="bus293" depart="410.20" departLane="best" departSpeed="5.00" from="E0" to="E1"/>
    <trip id="bus294" type="bus294" depart="411.60" departLane="best" departSpeed="5.00" from="E0" to="E1"/>
    <trip id="bus295" type="bus295" depart="413.00" departLane="best" departSpeed="5.00" from="E0" to="E1"/>
    <trip id="bus296" type="bus296" depart="414.40" departLane="best" departSpeed="5.00" from="E0" to="E1"/>
    <trip id="bus297" type="bus297" depart="415.80" departLane="best" departSpeed="5.00" from="E0" to="E1"/>
    <trip id="bus298" type="bus298" depart="417.20" departLane="best" departSpeed="5.00" from="E0" to="E1"/>
    <trip id="bus299" type="bus299" depart="418.60" departLane="best" departSpeed="5.00" from="E0" to="E1"/>
    <trip id="bus300" type="bus300" depart="420.00" departLane="best" departSpeed="5.00" from="E0" to="E1"/>
    <trip id="bus301" type="bus301" depart="421.40" departLane="best" departSpeed="5.00" from="E0" to="E1"/>
    <trip id="bus302" type="bus302" depart="422.80" departLane="best" departSpeed="5.00" from="E0" to="E1"/>
    <trip id="bus303" type="bus303" depart="424.20" departLane="best" departSpeed="5.00" from="E0" to="E1"/>
    <trip id="bus304" type="bus304" depart="425.60" departLane="best" departSpeed="5.00" from="E0" to="E1"/>
    <trip id="bus305" type="bus305" depart="427.00" departLane="best" departSpeed="5.00" from="E0" to="E1"/>
    <trip id="bus306" type="bus306" depart="428.40" departLane="best" departSpeed="5.00" from="E0" to="E1"/>
    <trip id="bus307" type="bus307" depart="429.80" departLane="best" departSpeed="5.00" from="E0" to="E1"/>
    <trip id="bus308" type="bus308" depart="431.20" departLane="best" departSpeed="5.00" from="E0" to="E1"/>
    <trip id="bus309" type="bus309" depart="432.60" departLane="best" departSpeed="5.00" from="E0" to="E1"/>
    <trip id="bus310" type="bus310" depart="434.00" departLane="best" departSpeed="5.00" from="E0" to="E1"/>
    <trip id="bus311" type="bus311" depart="435.40" departLane="best" departSpeed="5.00" from="E0" to="E1"/>
    <trip id="bus312" type="bus312" depart="436.80" departLane="best" departSpeed="5.00" from="E0" to="E1"/>
    <trip id="bus313" type="bus313" depart="438.20" departLane="best" departSpeed="5.00" from="E0" to="E1"/>
    <trip id="bus314" type="bus314" depart="439.60" departLane="best" departSpeed="5.00" from="E0" to="E1"/>
    <trip id="bus315" type="bus315" depart="441.00" departLane="best" departSpeed="5.00" from="E0" to="E1"/>
    <trip id="bus316" type="bus316" depart="442.40" departLane="best" departSpeed="5.00" from="E0" to="E1"/>
    <trip id="bus317" type="bus317" depart="443.80" departLane="best" departSpeed="5.00" from="E0" to="E1"/>
    <trip id="bus318" type="bus318" depart="445.20" departLane="best" departSpeed="5.00" from="E0" to="E1"/>
    <trip id="bus319" type="bus319" depart="446.60" departLane="best" departSpeed="5.00" from="E0" to="E1"/>
    <trip id="bus320" type="bus320" depart="448.00" departLane="best" departSpeed="5.00" from="E0" to="E1"/>
    <trip id="bus321" type="bus321" depart="449.40" departLane="best" departSpeed="5.00" from="E0" to="E1"/>
    <trip id="bus322" type="bus322" depart="450.80" departLane="best" departSpeed="5.00" from="E0" to="E1"/>
    <trip id="bus323" type="bus323" depart="452.20" departLane="best" departSpeed="5.00" from="E0" to="E1"/>
    <trip id="bus324" type="bus324" depart="453.60" departLane="best" departSpeed="5.00" from="E0" to="E1"/>
    <trip id="bus325" type="bus325" depart="455.00" departLane="best" departSpeed="5.00" from="E0" to="E1"/>
    <trip id="bus326" type="bus326" depart="456.40" departLane="best" departSpeed="5.00" from="E0" to="E1"/>
    <trip id="bus327" type="bus327" depart="457.80" departLane="best" departSpeed="5.00" from="E0" to="E1"/>
    <trip id="bus328" type="bus328" depart="459.20" departLane="best" departSpeed="5.00" from="E0" to="E1"/>
    <trip id="bus329" type="bus329" depart="460.60" departLane="best" departSpeed="5.00" from="E0" to="E1"/>
    <trip id="bus330" type="bus330" depart="462.00" departLane="best" departSpeed="5.00" from="E0" to="E1"/>
    <trip id="bus331" type="bus331" depart="463.40" departLane="best" departSpeed="5.00" from="E0" to="E1"/>
    <trip id="bus332" type="bus332" depart="464.80" departLane="best" departSpeed="5.00" from="E0" to="E1"/>
    <trip id="bus333" type="bus333" depart="466.20" departLane="best" departSpeed="5.00" from="E0" to="E1"/>
    <trip id="bus334" type="bus334" depart="467.60" departLane="best" departSpeed="5.00" from="E0" to="E1"/>
    <trip id="bus335" type="bus335" depart="469.00" departLane="best" departSpeed="5.00" from="E0" to="E1"/>
    <trip id="bus336" type="bus336" depart="470.40" departLane="best" departSpeed="5.00" from="E0" to="E1"/>
    <trip id="bus337" type="bus337" depart="471.80" departLane="best" departSpeed="5.00" from="E0" to="E1"/>
    <trip id="bus338" type="bus338" depart="473.20" departLane="best" departSpeed="5.00" from="E0" to="E1"/>
    <trip id="bus339" type="bus339" depart="474.60" departLane="best" departSpeed="5.00" from="E0" to="E1"/>
    <trip id="bus340" type="bus340" depart="476.00" departLane="best" departSpeed="5.00" from="E0" to="E1"/>
    <trip id="bus341" type="bus341" depart="477.40" departLane="best" departSpeed="5.00" from="E0" to="E1"/>
    <trip id="bus342" type="bus342" depart="478.80" departLane="best" departSpeed="5.00" from="E0" to="E1"/>
    <trip id="bus343" type="bus343" depart="480.20" departLane="best" departSpeed="5.00" from="E0" to="E1"/>
    <trip id="bus344" type="bus344" depart="481.60" departLane="best" departSpeed="5.00" from="E0" to="E1"/>
    <trip id="bus345" type="bus345" depart="483.00" departLane="best" departSpeed="5.00" from="E0" to="E1"/>
    <trip id="bus346" type="bus346" depart="484.40" departLane="best" departSpeed="5.00" from="E0" to="E1"/>
    <trip id="bus347" type="bus347" depart="485.80" departLane="best" departSpeed="5.00" from="E0" to="E1"/>
    <trip id="bus348" type="bus348" depart="487.20" departLane="best" departSpeed="5.00" from="E0" to="E1"/>
    <trip id="bus349" type="bus349" depart="488.60" departLane="best" departSpeed="5.00" from="E0" to="E1"/>
    <trip id="bus350" type="bus350" depart="490.00" departLane="best" departSpeed="5.00" from="E0" to="E1"/>
    <trip id="bus351" type="bus351" depart="491.40" departLane="best" departSpeed="5.00" from="E0" to="E1"/>
    <trip id="bus352" type="bus352" depart="492.80" departLane="best" departSpeed="5.00" from="E0" to="E1"/>
    <trip id="bus353" type="bus353" depart="494.20" departLane="best" departSpeed="5.00" from="E0" to="E1"/>
    <trip id="bus354" type="bus354" depart="495.60" departLane="best" departSpeed="5.00" from="E0" to="E1"/>
    <trip id="bus355" type="bus355" depart="497.00" departLane="best" departSpeed="5.00" from="E0" to="E1"/>
    <trip id="bus356" type="bus356" depart="498.40" departLane="best" departSpeed="5.00" from="E0" to="E1"/>
    <trip id="bus357" type="bus357" depart="499.80" departLane="best" departSpeed="5.00" from="E0" to="E1"/>
    <trip id="bus358" type="bus358" depart="501.20" departLane="best" departSpeed="5.00" from="E0" to="E1"/>
    <trip id="bus359" type="bus359" depart="502.60" departLane="best" departSpeed="5.00" from="E0" to="E1"/>
    <trip id="bus360" type="bus360" depart="504.00" departLane="best" departSpeed="5.00" from="E0" to="E1"/>
    <trip id="bus361" type="bus361" depart="505.40" departLane="best" departSpeed="5.00" from="E0" to="E1"/>
    <trip id="bus362" type="bus362" depart="506.80" departLane="best" departSpeed="5.00" from="E0" to="E1"/>
    <trip id="bus363" type="bus363" depart="508.20" departLane="best" departSpeed="5.00" from="E0" to="E1"/>
    <trip id="bus364" type="bus364" depart="509.60" departLane="best" departSpeed="5.00" from="E0" to="E1"/>
    <trip id="bus365" type="bus365" depart="511.00" departLane="best" departSpeed="5.00" from="E0" to="E1"/>
    <trip id="bus366" type="bus366" depart="512.40" departLane="best" departSpeed="5.00" from="E0" to="E1"/>
    <trip id="bus367" type="bus367" depart="513.80" departLane="best" departSpeed="5.00" from="E0" to="E1"/>
    <trip id="bus368" type="bus368" depart="515.20" departLane="best" departSpeed="5.00" from="E0" to="E1"/>
    <trip id="bus369" type="bus369" depart="516.60" departLane="best" departSpeed="5.00" from="E0" to="E1"/>
    <trip id="bus370" type="bus370" depart="518.00" departLane="best" departSpeed="5.00" from="E0" to="E1"/>
    <trip id="bus371" type="bus371" depart="519.40" departLane="best" departSpeed="5.00" from="E0" to="E1"/>
    <trip id="bus372" type="bus372" depart="520.80" departLane="best" departSpeed="5.00" from="E0" to="E1"/>
    <trip id="bus373" type="bus373" depart="522.20" departLane="best" departSpeed="5.00" from="E0" to="E1"/>
    <trip id="bus374" type="bus374" depart="523.60" departLane="best" departSpeed="5.00" from="E0" to="E1"/>
    <trip id="bus375" type="bus375" depart="525.00" departLane="best" departSpeed="5.00" from="E0" to="E1"/>
    <trip id="bus376" type="bus376" depart="526.40" departLane="best" departSpeed="5.00" from="E0" to="E1"/>
    <trip id="bus377" type="bus377" depart="527.80" departLane="best" departSpeed="5.00" from="E0" to="E1"/>
    <trip id="bus378" type="bus378" depart="529.20" departLane="best" departSpeed="5.00" from="E0" to="E1"/>
    <trip id="bus379" type="bus379" depart="530.60" departLane="best" departSpeed="5.00" from="E0" to="E1"/>
    <trip id="bus380" type="bus380" depart="532.00" departLane="best" departSpeed="5.00" from="E0" to="E1"/>
    <trip id="bus381" type="bus381" depart="533.40" departLane="best" departSpeed="5.00" from="E0" to="E1"/>
    <trip id="bus382" type="bus382" depart="534.80" departLane="best" departSpeed="5.00" from="E0" to="E1"/>
    <trip id="bus383" type="bus383" depart="536.20" departLane="best" departSpeed="5.00" from="E0" to="E1"/>
    <trip id="bus384" type="bus384" depart="537.60" departLane="best" departSpeed="5.00" from="E0" to="E1"/>
    <trip id="bus385" type="bus385" depart="539.00" departLane="best" departSpeed="5.00" from="E0" to="E1"/>
    <trip id="bus386" type="bus386" depart="540.40" departLane="best" departSpeed="5.00" from="E0" to="E1"/>
    <trip id="bus387" type="bus387" depart="541.80" departLane="best" departSpeed="5.00" from="E0" to="E1"/>
    <trip id="bus388" type="bus388" depart="543.20" departLane="best" departSpeed="5.00" from="E0" to="E1"/>
    <trip id="bus389" type="bus389" depart="544.60" departLane="best" departSpeed="5.00" from="E0" to="E1"/>
    <trip id="bus390" type="bus390" depart="546.00" departLane="best" departSpeed="5.00" from="E0" to="E1"/>
    <trip id="bus391" type="bus391" depart="547.40" departLane="best" departSpeed="5.00" from="E0" to="E1"/>
    <trip id="bus392" type="bus392" depart="548.80" departLane="best" departSpeed="5.00" from="E0" to="E1"/>
    <trip id="bus393" type="bus393" depart="550.20" departLane="best" departSpeed="5.00" from="E0" to="E1"/>
    <trip id="bus394" type="bus394" depart="551.60" departLane="best" departSpeed="5.00" from="E0" to="E1"/>
    <trip id="bus395" type="bus395" depart="553.00" departLane="best" departSpeed="5.00" from="E0" to="E1"/>
    <trip id="bus396" type="bus396" depart="554.40" departLane="best" departSpeed="5.00" from="E0" to="E1"/>
    <trip id="bus397" type="bus397" depart="555.80" departLane="best" departSpeed="5.00" from="E0" to="E1"/>
    <trip id="bus398" type="bus398" depart="557.20" departLane="best" departSpeed="5.00" from="E0" to="E1"/>
    <trip id="bus399" type="bus399" depart="558.60" departLane="best" departSpeed="5.00" from="E0" to="E1"/>
    <trip id="bus400" type="bus400" depart="560.00" departLane="best" departSpeed="5.00" from="E0" to="E1"/>
    <trip id="bus401" type="bus401" depart="561.40" departLane="best" departSpeed="5.00" from="E0" to="E1"/>
    <trip id="bus402" type="bus402" depart="562.80" departLane="best" departSpeed="5.00" from="E0" to="E1"/>
    <trip id="bus403" type="bus403" depart="564.20" departLane="best" departSpeed="5.00" from="E0" to="E1"/>
    <trip id="bus404" type="bus404" depart="565.60" departLane="best" departSpeed="5.00" from="E0" to="E1"/>
    <trip id="bus405" type="bus405" depart="567.00" departLane="best" departSpeed="5.00" from="E0" to="E1"/>
    <trip id="bus406" type="bus406" depart="568.40" departLane="best" departSpeed="5.00" from="E0" to="E1"/>
    <trip id="bus407" type="bus407" depart="569.80" departLane="best" departSpeed="5.00" from="E0" to="E1"/>
    <trip id="bus408" type="bus408" depart="571.20" departLane="best" departSpeed="5.00" from="E0" to="E1"/>
    <trip id="bus409" type="bus409" depart="572.60" departLane="best" departSpeed="5.00" from="E0" to="E1"/>
    <trip id="bus410" type="bus410" depart="574.00" departLane="best" departSpeed="5.00" from="E0" to="E1"/>
    <trip id="bus411" type="bus411" depart="575.40" departLane="best" departSpeed="5.00" from="E0" to="E1"/>
    <trip id="bus412" type="bus412" depart="576.80" departLane="best" departSpeed="5.00" from="E0" to="E1"/>
    <trip id="bus413" type="bus413" depart="578.20" departLane="best" departSpeed="5.00" from="E0" to="E1"/>
    <trip id="bus414" type="bus414" depart="579.60" departLane="best" departSpeed="5.00" from="E0" to="E1"/>
    <trip id="bus415" type="bus415" depart="581.00" departLane="best" departSpeed="5.00" from="E0" to="E1"/>
    <trip id="bus416" type="bus416" depart="582.40" departLane="best" departSpeed="5.00" from="E0" to="E1"/>
    <trip id="bus417" type="bus417" depart="583.80" departLane="best" departSpeed="5.00" from="E0" to="E1"/>
    <trip id="bus418" type="bus418" depart="585.20" departLane="best" departSpeed="5.00" from="E0" to="E1"/>
    <trip id="bus419" type="bus419" depart="586.60" departLane="best" departSpeed="5.00" from="E0" to="E1"/>
    <trip id="bus420" type="bus420" depart="588.00" departLane="best" departSpeed="5.00" from="E0" to="E1"/>
    <trip id="bus421" type="bus421" depart="589.40" departLane="best" departSpeed="5.00" from="E0" to="E1"/>
    <trip id="bus422" type="bus422" depart="590.80" departLane="best" departSpeed="5.00" from="E0" to="E1"/>
    <trip id="bus423" type="bus423" depart="592.20" departLane="best" departSpeed="5.00" from="E0" to="E1"/>
    <trip id="bus424" type="bus424" depart="593.60" departLane="best" departSpeed="5.00" from="E0" to="E1"/>
    <trip id="bus425" type="bus425" depart="595.00" departLane="best" departSpeed="5.00" from="E0" to="E1"/>
    <trip id="bus426" type="bus426" depart="596.40" departLane="best" departSpeed="5.00" from="E0" to="E1"/>
    <trip id="bus427" type="bus427" depart="597.80" departLane="best" departSpeed="5.00" from="E0" to="E1"/>
    <trip id="bus428" type="bus428" depart="599.20" departLane="best" departSpeed="5.00" from="E0" to="E1"/>
    <trip id="bus429" type="bus429" depart="600.60" departLane="best" departSpeed="5.00" from="E0" to="E1"/>
    <trip id="bus430" type="bus430" depart="602.00" departLane="best" departSpeed="5.00" from="E0" to="E1"/>
    <trip id="bus431" type="bus431" depart="603.40" departLane="best" departSpeed="5.00" from="E0" to="E1"/>
    <trip id="bus432" type="bus432" depart="604.80" departLane="best" departSpeed="5.00" from="E0" to="E1"/>
    <trip id="bus433" type="bus433" depart="606.20" departLane="best" departSpeed="5.00" from="E0" to="E1"/>
    <trip id="bus434" type="bus434" depart="607.60" departLane="best" departSpeed="5.00" from="E0" to="E1"/>
    <trip id="bus435" type="bus435" depart="609.00" departLane="best" departSpeed="5.00" from="E0" to="E1"/>
    <trip id="bus436" type="bus436" depart="610.40" departLane="best" departSpeed="5.00" from="E0" to="E1"/>
    <trip id="bus437" type="bus437" depart="611.80" departLane="best" departSpeed="5.00" from="E0" to="E1"/>
    <trip id="bus438" type="bus438" depart="613.20" departLane="best" departSpeed="5.00" from="E0" to="E1"/>
    <trip id="bus439" type="bus439" depart="614.60" departLane="best" departSpeed="5.00" from="E0" to="E1"/>
    <trip id="bus440" type="bus440" depart="616.00" departLane="best" departSpeed="5.00" from="E0" to="E1"/>
    <trip id="bus441" type="bus441" depart="617.40" departLane="best" departSpeed="5.00" from="E0" to="E1"/>
    <trip id="bus442" type="bus442" depart="618.80" departLane="best" departSpeed="5.00" from="E0" to="E1"/>
    <trip id="bus443" type="bus443" depart="620.20" departLane="best" departSpeed="5.00" from="E0" to="E1"/>
    <trip id="bus444" type="bus444" depart="621.60" departLane="best" departSpeed="5.00" from="E0" to="E1"/>
    <trip id="bus445" type="bus445" depart="623.00" departLane="best" departSpeed="5.00" from="E0" to="E1"/>
    <trip id="bus446" type="bus446" depart="624.40" departLane="best" departSpeed="5.00" from="E0" to="E1"/>
    <trip id="bus447" type="bus447" depart="625.80" departLane="best" departSpeed="5.00" from="E0" to="E1"/>
    <trip id="bus448" type="bus448" depart="627.20" departLane="best" departSpeed="5.00" from="E0" to="E1"/>
    <trip id="bus449" type="bus449" depart="628.60" departLane="best" departSpeed="5.00" from="E0" to="E1"/>
    <trip id="bus450" type="bus450" depart="630.00" departLane="best" departSpeed="5.00" from="E0" to="E1"/>
    <trip id="bus451" type="bus451" depart="631.40" departLane="best" departSpeed="5.00" from="E0" to="E1"/>
    <trip id="bus452" type="bus452" depart="632.80" departLane="best" departSpeed="5.00" from="E0" to="E1"/>
    <trip id="bus453" type="bus453" depart="634.20" departLane="best" departSpeed="5.00" from="E0" to="E1"/>
    <trip id="bus454" type="bus454" depart="635.60" departLane="best" departSpeed="5.00" from="E0" to="E1"/>
    <trip id="bus455" type="bus455" depart="637.00" departLane="best" departSpeed="5.00" from="E0" to="E1"/>
    <trip id="bus456" type="bus456" depart="638.40" departLane="best" departSpeed="5.00" from="E0" to="E1"/>
    <trip id="bus457" type="bus457" depart="639.80" departLane="best" departSpeed="5.00" from="E0" to="E1"/>
    <trip id="bus458" type="bus458" depart="641.20" departLane="best" departSpeed="5.00" from="E0" to="E1"/>
    <trip id="bus459" type="bus459" depart="642.60" departLane="best" departSpeed="5.00" from="E0" to="E1"/>
    <trip id="bus460" type="bus460" depart="644.00" departLane="best" departSpeed="5.00" from="E0" to="E1"/>
    <trip id="bus461" type="bus461" depart="645.40" departLane="best" departSpeed="5.00" from="E0" to="E1"/>
    <trip id="bus462" type="bus462" depart="646.80" departLane="best" departSpeed="5.00" from="E0" to="E1"/>
    <trip id="bus463" type="bus463" depart="648.20" departLane="best" departSpeed="5.00" from="E0" to="E1"/>
    <trip id="bus464" type="bus464" depart="649.60" departLane="best" departSpeed="5.00" from="E0" to="E1"/>
    <trip id="bus465" type="bus465" depart="651.00" departLane="best" departSpeed="5.00" from="E0" to="E1"/>
    <trip id="bus466" type="bus466" depart="652.40" departLane="best" departSpeed="5.00" from="E0" to="E1"/>
    <trip id="bus467" type="bus467" depart="653.80" departLane="best" departSpeed="5.00" from="E0" to="E1"/>
    <trip id="bus468" type="bus468" depart="655.20" departLane="best" departSpeed="5.00" from="E0" to="E1"/>
    <trip id="bus469" type="bus469" depart="656.60" departLane="best" departSpeed="5.00" from="E0" to="E1"/>
    <trip id="bus470" type="bus470" depart="658.00" departLane="best" departSpeed="5.00" from="E0" to="E1"/>
    <trip id="bus471" type="bus471" depart="659.40" departLane="best" departSpeed="5.00" from="E0" to="E1"/>
    <trip id="bus472" type="bus472" depart="660.80" departLane="best" departSpeed="5.00" from="E0" to="E1"/>
    <trip id="bus473" type="bus473" depart="662.20" departLane="best" departSpeed="5.00" from="E0" to="E1"/>
    <trip id="bus474" type="bus474" depart="663.60" departLane="best" departSpeed="5.00" from="E0" to="E1"/>
    <trip id="bus475" type="bus475" depart="665.00" departLane="best" departSpeed="5.00" from="E0" to="E1"/>
    <trip id="bus476" type="bus476" depart="666.40" departLane="best" departSpeed="5.00" from="E0" to="E1"/>
    <trip id="bus477" type="bus477" depart="667.80" departLane="best" departSpeed="5.00" from="E0" to="E1"/>
    <trip id="bus478" type="bus478" depart="669.20" departLane="best" departSpeed="5.00" from="E0" to="E1"/>
    <trip id="bus479" type="bus479" depart="670.60" departLane="best" departSpeed="5.00" from="E0" to="E1"/>
    <trip id="bus480" type="bus480" depart="672.00" departLane="best" departSpeed="5.00" from="E0" to="E1"/>
    <trip id="bus481" type="bus481" depart="673.40" departLane="best" departSpeed="5.00" from="E0" to="E1"/>
    <trip id="bus482" type="bus482" depart="674.80" departLane="best" departSpeed="5.00" from="E0" to="E1"/>
    <trip id="bus483" type="bus483" depart="676.20" departLane="best" departSpeed="5.00" from="E0" to="E1"/>
    <trip id="bus484" type="bus484" depart="677.60" departLane="best" departSpeed="5.00" from="E0" to="E1"/>
    <trip id="bus485" type="bus485" depart="679.00" departLane="best" departSpeed="5.00" from="E0" to="E1"/>
    <trip id="bus486" type="bus486" depart="680.40" departLane="best" departSpeed="5.00" from="E0" to="E1"/>
    <trip id="bus487" type="bus487" depart="681.80" departLane="best" departSpeed="5.00" from="E0" to="E1"/>
    <trip id="bus488" type="bus488" depart="683.20" departLane="best" departSpeed="5.00" from="E0" to="E1"/>
    <trip id="bus489" type="bus489" depart="684.60" departLane="best" departSpeed="5.00" from="E0" to="E1"/>
    <trip id="bus490" type="bus490" depart="686.00" departLane="best" departSpeed="5.00" from="E0" to="E1"/>
    <trip id="bus491" type="bus491" depart="687.40" departLane="best" departSpeed="5.00" from="E0" to="E1"/>
    <trip id="bus492" type="bus492" depart="688.80" departLane="best" departSpeed="5.00" from="E0" to="E1"/>
    <trip id="bus493" type="bus493" depart="690.20" departLane="best" departSpeed="5.00" from="E0" to="E1"/>
    <trip id="bus494" type="bus494" depart="691.60" departLane="best" departSpeed="5.00" from="E0" to="E1"/>
    <trip id="bus495" type="bus495" depart="693.00" departLane="best" departSpeed="5.00" from="E0" to="E1"/>
    <trip id="bus496" type="bus496" depart="694.40" departLane="best" departSpeed="5.00" from="E0" to="E1"/>
    <trip id="bus497" type="bus497" depart="695.80" departLane="best" departSpeed="5.00" from="E0" to="E1"/>
    <trip id="bus498" type="bus498" depart="697.20" departLane="best" departSpeed="5.00" from="E0" to="E1"/>
    <trip id="bus499" type="bus499" depart="698.60" departLane="best" departSpeed="5.00" from="E0" to="E1"/>
    <trip id="bus500" type="bus500" depart="700.00" departLane="best" departSpeed="5.00" from="E0" to="E1"/>
    <trip id="bus501" type="bus501" depart="701.40" departLane="best" departSpeed="5.00" from="E0" to="E1"/>
    <trip id="bus502" type="bus502" depart="702.80" departLane="best" departSpeed="5.00" from="E0" to="E1"/>
    <trip id="bus503" type="bus503" depart="704.20" departLane="best" departSpeed="5.00" from="E0" to="E1"/>
    <trip id="bus504" type="bus504" depart="705.60" departLane="best" departSpeed="5.00" from="E0" to="E1"/>
    <trip id="bus505" type="bus505" depart="707.00" departLane="best" departSpeed="5.00" from="E0" to="E1"/>
    <trip id="bus506" type="bus506" depart="708.40" departLane="best" departSpeed="5.00" from="E0" to="E1"/>
    <trip id="bus507" type="bus507" depart="709.80" departLane="best" departSpeed="5.00" from="E0" to="E1"/>
    <trip id="bus508" type="bus508" depart="711.20" departLane="best" departSpeed="5.00" from="E0" to="E1"/>
    <trip id="bus509" type="bus509" depart="712.60" departLane="best" departSpeed="5.00" from="E0" to="E1"/>
    <trip id="bus510" type="bus510" depart="714.00" departLane="best" departSpeed="5.00" from="E0" to="E1"/>
    <trip id="bus511" type="bus511" depart="715.40" departLane="best" departSpeed="5.00" from="E0" to="E1"/>
    <trip id="bus512" type="bus512" depart="716.80" departLane="best" departSpeed="5.00" from="E0" to="E1"/>
    <trip id="bus513" type="bus513" depart="718.20" departLane="best" departSpeed="5.00" from="E0" to="E1"/>
    <trip id="bus514" type="bus514" depart="719.60" departLane="best" departSpeed="5.00" from="E0" to="E1"/>
    <trip id="bus515" type="bus515" depart="721.00" departLane="best" departSpeed="5.00" from="E0" to="E1"/>
    <trip id="bus516" type="bus516" depart="722.40" departLane="best" departSpeed="5.00" from="E0" to="E1"/>
    <trip id="bus517" type="bus517" depart="723.80" departLane="best" departSpeed="5.00" from="E0" to="E1"/>
    <trip id="bus518" type="bus518" depart="725.20" departLane="best" departSpeed="5.00" from="E0" to="E1"/>
    <trip id="bus519" type="bus519" depart="726.60" departLane="best" departSpeed="5.00" from="E0" to="E1"/>
    <trip id="bus520" type="bus520" depart="728.00" departLane="best" departSpeed="5.00" from="E0" to="E1"/>
    <trip id="bus521" type="bus521" depart="729.40" departLane="best" departSpeed="5.00" from="E0" to="E1"/>
    <trip id="bus522" type="bus522" depart="730.80" departLane="best" departSpeed="5.00" from="E0" to="E1"/>
    <trip id="bus523" type="bus523" depart="732.20" departLane="best" departSpeed="5.00" from="E0" to="E1"/>
    <trip id="bus524" type="bus524" depart="733.60" departLane="best" departSpeed="5.00" from="E0" to="E1"/>
    <trip id="bus525" type="bus525" depart="735.00" departLane="best" departSpeed="5.00" from="E0" to="E1"/>
    <trip id="bus526" type="bus526" depart="736.40" departLane="best" departSpeed="5.00" from="E0" to="E1"/>
    <trip id="bus527" type="bus527" depart="737.80" departLane="best" departSpeed="5.00" from="E0" to="E1"/>
    <trip id="bus528" type="bus528" depart="739.20" departLane="best" departSpeed="5.00" from="E0" to="E1"/>
    <trip id="bus529" type="bus529" depart="740.60" departLane="best" departSpeed="5.00" from="E0" to="E1"/>
    <trip id="bus530" type="bus530" depart="742.00" departLane="best" departSpeed="5.00" from="E0" to="E1"/>
    <trip id="bus531" type="bus531" depart="743.40" departLane="best" departSpeed="5.00" from="E0" to="E1"/>
    <trip id="bus532" type="bus532" depart="744.80" departLane="best" departSpeed="5.00" from="E0" to="E1"/>
    <trip id="bus533" type="bus533" depart="746.20" departLane="best" departSpeed="5.00" from="E0" to="E1"/>
    <trip id="bus534" type="bus534" depart="747.60" departLane="best" departSpeed="5.00" from="E0" to="E1"/>
    <trip id="bus535" type="bus535" depart="749.00" departLane="best" departSpeed="5.00" from="E0" to="E1"/>
    <trip id="bus536" type="bus536" depart="750.40" departLane="best" departSpeed="5.00" from="E0" to="E1"/>
    <trip id="bus537" type="bus537" depart="751.80" departLane="best" departSpeed="5.00" from="E0" to="E1"/>
    <trip id="bus538" type="bus538" depart="753.20" departLane="best" departSpeed="5.00" from="E0" to="E1"/>
    <trip id="bus539" type="bus539" depart="754.60" departLane="best" departSpeed="5.00" from="E0" to="E1"/>
    <trip id="bus540" type="bus540" depart="756.00" departLane="best" departSpeed="5.00" from="E0" to="E1"/>
    <trip id="bus541" type="bus541" depart="757.40" departLane="best" departSpeed="5.00" from="E0" to="E1"/>
    <trip id="bus542" type="bus542" depart="758.80" departLane="best" departSpeed="5.00" from="E0" to="E1"/>
    <trip id="bus543" type="bus543" depart="760.20" departLane="best" departSpeed="5.00" from="E0" to="E1"/>
    <trip id="bus544" type="bus544" depart="761.60" departLane="best" departSpeed="5.00" from="E0" to="E1"/>
    <trip id="bus545" type="bus545" depart="763.00" departLane="best" departSpeed="5.00" from="E0" to="E1"/>
    <trip id="bus546" type="bus546" depart="764.40" departLane="best" departSpeed="5.00" from="E0" to="E1"/>
    <trip id="bus547" type="bus547" depart="765.80" departLane="best" departSpeed="5.00" from="E0" to="E1"/>
    <trip id="bus548" type="bus548" depart="767.20" departLane="best" departSpeed="5.00" from="E0" to="E1"/>
    <trip id="bus549" type="bus549" depart="768.60" departLane="best" departSpeed="5.00" from="E0" to="E1"/>
    <trip id="bus550" type="bus550" depart="770.00" departLane="best" departSpeed="5.00" from="E0" to="E1"/>
    <trip id="bus551" type="bus551" depart="771.40" departLane="best" departSpeed="5.00" from="E0" to="E1"/>
    <trip id="bus552" type="bus552" depart="772.80" departLane="best" departSpeed="5.00" from="E0" to="E1"/>
    <trip id="bus553" type="bus553" depart="774.20" departLane="best" departSpeed="5.00" from="E0" to="E1"/>
    <trip id="bus554" type="bus554" depart="775.60" departLane="best" departSpeed="5.00" from="E0" to="E1"/>
    <trip id="bus555" type="bus555" depart="777.00" departLane="best" departSpeed="5.00" from="E0" to="E1"/>
    <trip id="bus556" type="bus556" depart="778.40" departLane="best" departSpeed="5.00" from="E0" to="E1"/>
    <trip id="bus557" type="bus557" depart="779.80" departLane="best" departSpeed="5.00" from="E0" to="E1"/>
    <trip id="bus558" type="bus558" depart="781.20" departLane="best" departSpeed="5.00" from="E0" to="E1"/>
    <trip id="bus559" type="bus559" depart="782.60" departLane="best" departSpeed="5.00" from="E0" to="E1"/>
    <trip id="bus560" type="bus560" depart="784.00" departLane="best" departSpeed="5.00" from="E0" to="E1"/>
    <trip id="bus561" type="bus561" depart="785.40" departLane="best" departSpeed="5.00" from="E0" to="E1"/>
    <trip id="bus562" type="bus562" depart="786.80" departLane="best" departSpeed="5.00" from="E0" to="E1"/>
    <trip id="bus563" type="bus563" depart="788.20" departLane="best" departSpeed="5.00" from="E0" to="E1"/>
    <trip id="bus564" type="bus564" depart="789.60" departLane="best" departSpeed="5.00" from="E0" to="E1"/>
    <trip id="bus565" type="bus565" depart="791.00" departLane="best" departSpeed="5.00" from="E0" to="E1"/>
    <trip id="bus566" type="bus566" depart="792.40" departLane="best" departSpeed="5.00" from="E0" to="E1"/>
    <trip id="bus567" type="bus567" depart="793.80" departLane="best" departSpeed="5.00" from="E0" to="E1"/>
    <trip id="bus568" type="bus568" depart="795.20" departLane="best" departSpeed="5.00" from="E0" to="E1"/>
    <trip id="bus569" type="bus569" depart="796.60" departLane="best" departSpeed="5.00" from="E0" to="E1"/>
    <trip id="bus570" type="bus570" depart="798.00" departLane="best" departSpeed="5.00" from="E0" to="E1"/>
    <trip id="bus571" type="bus571" depart="799.40" departLane="best" departSpeed="5.00" from="E0" to="E1"/>
    <trip id="bus572" type="bus572" depart="800.80" departLane="best" departSpeed="5.00" from="E0" to="E1"/>
    <trip id="bus573" type="bus573" depart="802.20" departLane="best" departSpeed="5.00" from="E0" to="E1"/>
    <trip id="bus574" type="bus574" depart="803.60" departLane="best" departSpeed="5.00" from="E0" to="E1"/>
    <trip id="bus575" type="bus575" depart="805.00" departLane="best" departSpeed="5.00" from="E0" to="E1"/>
    <trip id="bus576" type="bus576" depart="806.40" departLane="best" departSpeed="5.00" from="E0" to="E1"/>
    <trip id="bus577" type="bus577" depart="807.80" departLane="best" departSpeed="5.00" from="E0" to="E1"/>
    <trip id="bus578" type="bus578" depart="809.20" departLane="best" departSpeed="5.00" from="E0" to="E1"/>
    <trip id="bus579" type="bus579" depart="810.60" departLane="best" departSpeed="5.00" from="E0" to="E1"/>
    <trip id="bus580" type="bus580" depart="812.00" departLane="best" departSpeed="5.00" from="E0" to="E1"/>
    <trip id="bus581" type="bus581" depart="813.40" departLane="best" departSpeed="5.00" from="E0" to="E1"/>
    <trip id="bus582" type="bus582" depart="814.80" departLane="best" departSpeed="5.00" from="E0" to="E1"/>
    <trip id="bus583" type="bus583" depart="816.20" departLane="best" departSpeed="5.00" from="E0" to="E1"/>
    <trip id="bus584" type="bus584" depart="817.60" departLane="best" departSpeed="5.00" from="E0" to="E1"/>
    <trip id="bus585" type="bus585" depart="819.00" departLane="best" departSpeed="5.00" from="E0" to="E1"/>
    <trip id="bus586" type="bus586" depart="820.40" departLane="best" departSpeed="5.00" from="E0" to="E1"/>
    <trip id="bus587" type="bus587" depart="821.80" departLane="best" departSpeed="5.00" from="E0" to="E1"/>
    <trip id="bus588" type="bus588" depart="823.20" departLane="best" departSpeed="5.00" from="E0" to="E1"/>
    <trip id="bus589" type="bus589" depart="824.60" departLane="best" departSpeed="5.00" from="E0" to="E1"/>
    <trip id="bus590" type="bus590" depart="826.00" departLane="best" departSpeed="5.00" from="E0" to="E1"/>
    <trip id="bus591" type="bus591" depart="827.40" departLane="best" departSpeed="5.00" from="E0" to="E1"/>
    <trip id="bus592" type="bus592" depart="828.80" departLane="best" departSpeed="5.00" from="E0" to="E1"/>
    <trip id="bus593" type="bus593" depart="830.20" departLane="best" departSpeed="5.00" from="E0" to="E1"/>
    <trip id="bus594" type="bus594" depart="831.60" departLane="best" departSpeed="5.00" from="E0" to="E1"/>
    <trip id="bus595" type="bus595" depart="833.00" departLane="best" departSpeed="5.00" from="E0" to="E1"/>
    <trip id="bus596" type="bus596" depart="834.40" departLane="best" departSpeed="5.00" from="E0" to="E1"/>
    <trip id="bus597" type="bus597" depart="835.80" departLane="best" departSpeed="5.00" from="E0" to="E1"/>
    <trip id="bus598" type="bus598" depart="837.20" departLane="best" departSpeed="5.00" from="E0" to="E1"/>
    <trip id="bus599" type="bus599" depart="838.60" departLane="best" departSpeed="5.00" from="E0" to="E1"/>
    <trip id="bus600" type="bus600" depart="840.00" departLane="best" departSpeed="5.00" from="E0" to="E1"/>
    <trip id="bus601" type="bus601" depart="841.40" departLane="best" departSpeed="5.00" from="E0" to="E1"/>
    <trip id="bus602" type="bus602" depart="842.80" departLane="best" departSpeed="5.00" from="E0" to="E1"/>
    <trip id="bus603" type="bus603" depart="844.20" departLane="best" departSpeed="5.00" from="E0" to="E1"/>
    <trip id="bus604" type="bus604" depart="845.60" departLane="best" departSpeed="5.00" from="E0" to="E1"/>
    <trip id="bus605" type="bus605" depart="847.00" departLane="best" departSpeed="5.00" from="E0" to="E1"/>
    <trip id="bus606" type="bus606" depart="848.40" departLane="best" departSpeed="5.00" from="E0" to="E1"/>
    <trip id="bus607" type="bus607" depart="849.80" departLane="best" departSpeed="5.00" from="E0" to="E1"/>
    <trip id="bus608" type="bus608" depart="851.20" departLane="best" departSpeed="5.00" from="E0" to="E1"/>
    <trip id="bus609" type="bus609" depart="852.60" departLane="best" departSpeed="5.00" from="E0" to="E1"/>
</routes>
